<?xml version="1.0" encoding="UTF-8"?>
<!DOCTYPE properties SYSTEM "http://java.sun.com/dtd/properties.dtd">
<properties>
<entry key="PC.MAL.MW_H_001">메일 쓰기</entry>
<entry key="PC.MAL.MW_C_002">임시보관함에 자동 저장된 메일이 있습니다. 해당 메일을 불러오시겠습니까?</entry>
<entry key="PC.MAL.MW_C_003">(취소 시 자동 저장된 메일은 삭제됩니다.)</entry>
<entry key="PC.MAL.MW_C_004">확인</entry>
<entry key="PC.MAL.MW_C_005">취소</entry>
<entry key="PC.MAL.MW_H_006">보내기</entry>
<entry key="PC.MAL.MW_H_007">임시저장</entry>
<entry key="PC.MAL.MW_H_008">제목</entry>
<entry key="PC.MAL.MW_H_009">보내는사람</entry>
<entry key="PC.MAL.MW_H_010">받는사람</entry>
<entry key="PC.MAL.MW_H_011">참조</entry>
<entry key="PC.MAL.MW_H_012">숨은참조</entry>
<entry key="PC.MAL.MW_H_013">첨부파일</entry>
<entry key="PC.MAL.MW_H_014">중요</entry>
<entry key="PC.MAL.MW_H_015">약속잡기</entry>
<entry key="PC.MAL.MW_H_016">약속</entry>
<entry key="PC.MAL.MW_H_017">시작일시</entry>
<entry key="PC.MAL.MW_H_018">종료일시</entry>
<entry key="PC.MAL.MW_H_019">약속장소</entry>
<entry key="PC.MAL.MW_H_020">확인</entry>
<entry key="PC.MAL.MW_H_021">취소</entry>
<entry key="PC.MAL.MW_H_022">YYYY/MM/DD/ 오전 / 오후 HH:MM</entry>
<entry key="PC.MAL.MW_H_023">메일 발송 시 일정에 등록이 되며 수신자는 메일 읽었을 때 일정에 등록이 됩니다.</entry>
<entry key="PC.MAL.MW_H_024">예약발송</entry>
<entry key="PC.MAL.MW_H_025">개별발송</entry>
<entry key="PC.MAL.MW_H_026">수신확인</entry>
<entry key="PC.MAL.MW_H_027">주소록추가</entry>
<entry key="PC.MAL.MW_H_028">나에게도 발송</entry>
<entry key="PC.MAL.MW_H_029">최근주소</entry>
<entry key="PC.MAL.MW_H_030">최근 사용(받는사람만 적용)</entry>
<entry key="PC.MAL.MW_H_031">주소록</entry>
<entry key="PC.MAL.MW_H_032">수신자 선택</entry>
<entry key="PC.MAL.MW_H_033">주소록</entry>
<entry key="PC.MAL.MW_H_034">검색</entry>
<entry key="PC.MAL.MW_H_035">총 X명 선택</entry>
<entry key="PC.MAL.MW_H_036">삭제</entry>
<entry key="PC.MAL.MW_H_037">적용</entry>
<entry key="PC.MAL.MW_H_038">취소</entry>
<entry key="PC.MAL.MW_H_039">조직도</entry>
<entry key="PC.MAL.MW_H_040">수신자 선택</entry>
<entry key="PC.MAL.MW_H_041">조직도</entry>
<entry key="PC.MAL.MW_H_042">내 그룹</entry>
<entry key="PC.MAL.MW_H_043">검색</entry>
<entry key="PC.MAL.MW_H_044">총 X명 선택</entry>
<entry key="PC.MAL.MW_H_045">전사관리자</entry>
<entry key="PC.MAL.MW_H_046">부서장</entry>
<entry key="PC.MAL.MW_H_047">삭제</entry>
<entry key="PC.MAL.MW_H_048">적용</entry>
<entry key="PC.MAL.MW_H_049">취소</entry>
<entry key="PC.MAL.MW_H_050">받는사람이 여러명일 경우 쉼표(,) 혹은 세미콜론(;)으로 구분합니다.</entry>
<entry key="PC.MAL.MW_H_051">보안메일</entry>
<entry key="PC.MAL.MW_H_052">사용</entry>
<entry key="PC.MAL.MW_H_053">인증번호입력</entry>
<entry key="PC.MAL.MW_H_054">숫자 4자리</entry>
<entry key="PC.MAL.MW_H_055">힌트</entry>
<entry key="PC.MAL.MW_H_056">숫자 또는 문자 50자 이내</entry>
<entry key="PC.MAL.MW_A_057">비밀번호는 숫자 4자리로 입력해 주세요.</entry>
<entry key="PC.MAL.MW_A_058">확인</entry>
<entry key="PC.MAL.MW_H_059">내 PC</entry>
<entry key="PC.MAL.MW_H_060">웹디스크</entry>
<entry key="PC.MAL.MW_H_061">U+BOX</entry>
<entry key="PC.MAL.MW_H_062">일반첨부</entry>
<entry key="PC.MAL.MW_H_063">대용량첨부</entry>
<entry key="PC.MAL.MW_H_064">전환</entry>
<entry key="PC.MAL.MW_H_065">삭제</entry>
<entry key="PC.MAL.MW_H_066">업로드 진행중…</entry>
<entry key="PC.MAL.MW_A_067">업로드가 완료된 후 사디 시도해주세요.</entry>
<entry key="PC.MAL.MW_A_068">확인</entry>
<entry key="PC.MAL.MW_H_069">필수 입력 항목입니다.</entry>
<entry key="PC.MAL.MW_H_070">마우스로 파일을 끌어오셔서 내 PC에 올려 놓으면 파일이 첨부됩니다. IE : v.10 이상 지원 Firefox : v.4+ 이상 지원 Chrome : 모두 지원 Safari : Mac OS  만 지원 Opera : 모두 지원</entry>
<entry key="PC.MAL.MW_H_071">이곳에 놓으세요.</entry>
<entry key="PC.MAL.MW_H_072">편집</entry>
<entry key="PC.MAL.MW_H_073">HTML</entry>
<entry key="PC.MAL.MW_H_074">미리보기</entry>
<entry key="PC.MAL.MW_T_075">임시보관함에 저장되었습니다.</entry>
<entry key="PC.MAL.MW_T_076">메일을 발송하였습니다.</entry>
<entry key="PC.MAL.MW_C_077">예약메일이 등록되었습니다.</entry>
<entry key="PC.MAL.MW_C_078">작성을 중지하시겠습니까?</entry>
<entry key="PC.MAL.MW_C_079">확인</entry>
<entry key="PC.MAL.MW_C_079">취소</entry>
<entry key="PC.MAL.MI_H_001">받은편지함</entry>
<entry key="PC.MAL.MI_H_002">제목</entry>
<entry key="PC.MAL.MI_H_003">보낸사람</entry>
<entry key="PC.MAL.MI_H_004">크기</entry>
<entry key="PC.MAL.MI_H_005">받은날짜</entry>
<entry key="PC.MAL.MI_H_006">총 X건 중 X-X번째</entry>
<entry key="PC.MAL.MI_H_007">전체메일</entry>
<entry key="PC.MAL.MI_H_008">읽지않은메일</entry>
<entry key="PC.MAL.MI_H_009">읽은메일</entry>
<entry key="PC.MAL.MI_H_010">알림 메일제외</entry>
<entry key="PC.MAL.MI_H_011">삭제</entry>
<entry key="PC.MAL.MI_H_012">스팸차단</entry>
<entry key="PC.MAL.MI_H_013">이동</entry>
<entry key="PC.MAL.MI_H_014">상태변경</entry>
<entry key="PC.MAL.MI_H_015">읽음</entry>
<entry key="PC.MAL.MI_H_016">읽지않음</entry>
<entry key="PC.MAL.MI_H_017">추가기능</entry>
<entry key="PC.MAL.MI_H_018">일정 등록</entry>
<entry key="PC.MAL.MI_H_019">할일 요청</entry>
<entry key="PC.MAL.MI_H_020">PC로 저장</entry>
<entry key="PC.MAL.MI_H_021">답장</entry>
<entry key="PC.MAL.MI_H_022">전체답장</entry>
<entry key="PC.MAL.MI_H_023">전달</entry>
<entry key="PC.MAL.MI_C_024">다중전달</entry>
<entry key="PC.MAL.MI_C_024">메일을 삭제하시겠습니까?</entry>
<entry key="PC.MAL.MI_C_025">확인</entry>
<entry key="PC.MAL.MI_C_026">취소</entry>
<entry key="PC.MAL.MI_T_027">메일이 삭제되었습니다.</entry>
<entry key="PC.MAL.MI_C_028">보낸사람의 이메일주소가 수신거부에 등록 됩니다. 보낸사람을 스팸차단 하시겠습니까?</entry>
<entry key="PC.MAL.MI_C_029">확인</entry>
<entry key="PC.MAL.MI_C_030">취소</entry>
<entry key="PC.MAL.MI_T_031">수신거부 목록에 등록되었습니다.</entry>
<entry key="PC.MAL.MI_T_032">메일이 이동되었습니다.</entry>
<entry key="PC.MAL.MI_C_033">메일을 작성 중입니다. 작성을 중지하고 답장 메일을 쓰시겠습니까?</entry>
<entry key="PC.MAL.MI_C_034">확인</entry>
<entry key="PC.MAL.MI_C_035">취소</entry>
<entry key="PC.MAL.MI_C_036">메일을 작성 중입니다. 작성을 중지하고 전체답장 메일을 쓰시겠습니까?</entry>
<entry key="PC.MAL.MI_C_037">확인</entry>
<entry key="PC.MAL.MI_C_038">취소</entry>
<entry key="PC.MAL.MI_C_039">메일을 작성 중입니다. 작성을 중지하고 전달 메일을 쓰시겠습니까?</entry>
<entry key="PC.MAL.MI_C_040">확인</entry>
<entry key="PC.MAL.MI_C_041">취소</entry>
<entry key="PC.MAL.MI_C_042">메일을 작성 중입니다. 작성을 중지하고 다중전달 메일을 쓰시겠습니까?</entry>
<entry key="PC.MAL.MI_C_043">(메일 크기와 개수에 따라 다소 시간이 소요됩니다.)</entry>
<entry key="PC.MAL.MI_C_044">확인</entry>
<entry key="PC.MAL.MI_C_045">취소</entry>
<entry key="PC.MAL.MI_C_046">다중전달 메일을 쓰시겠습니까? (메일 크기와 개수에 따라 다소 시간이 소요됩니다.</entry>
<entry key="PC.MAL.MI_C_047">확인</entry>
<entry key="PC.MAL.MI_C_048">취소</entry>
<entry key="PC.MAL.MI_A_049">다중전달 메일은 10개까지 선택 가능합니다.</entry>
<entry key="PC.MAL.MI_A_050">확인</entry>
<entry key="PC.MAL.MI_MT_H_001">답장</entry>
<entry key="PC.MAL.MI_MT_H_002">전체답장</entry>
<entry key="PC.MAL.MI_MT_H_003">전달</entry>
<entry key="PC.MAL.MI_MT_H_004">삭제</entry>
<entry key="PC.MAL.MI_MT_H_005">스팸차단</entry>
<entry key="PC.MAL.MI_MT_H_006">읽지않음</entry>
<entry key="PC.MAL.MI_MT_H_007">이동</entry>
<entry key="PC.MAL.MI_MT_H_008">추가기능</entry>
<entry key="PC.MAL.MI_MT_H_009">일정 등록</entry>
<entry key="PC.MAL.MI_MT_H_010">할일 요청</entry>
<entry key="PC.MAL.MI_MT_H_011">PC로 저장</entry>
<entry key="PC.MAL.MI_MT_H_012">인쇄</entry>
<entry key="PC.MAL.MI_MT_H_013">원문보기</entry>
<entry key="PC.MAL.MI_MT_H_014">이전</entry>
<entry key="PC.MAL.MI_MT_H_015">목록</entry>
<entry key="PC.MAL.MI_MT_H_016">다음</entry>
<entry key="PC.MAL.MI_MT_H_014">제목</entry>
<entry key="PC.MAL.MI_MT_H_015">보낸사람</entry>
<entry key="PC.MAL.MI_MT_H_016">받은날짜</entry>
<entry key="PC.MAL.MI_MT_H_017">받는사람</entry>
<entry key="PC.MAL.MI_MT_H_018">첨부파일</entry>
<entry key="PC.MAL.MI_MT_H_019">본문 크기 조절</entry>
<entry key="PC.MAL.MI_MT_H_020">전체</entry>
<entry key="PC.MAL.MI_MT_H_021">A4 세로</entry>
<entry key="PC.MAL.MI_MT_H_022">본문 팝업</entry>
<entry key="PC.MAL.MI_MT_H_023">원문접수</entry>
<entry key="PC.MAL.MI_MT_H_024">원문접수</entry>
<entry key="PC.MAL.MI_MT_H_025">메일 원문을 고객센터로 접수 하기위해서는 아래 정보를 반드시 입력하셔야 하며, 발송 전 고객센터와 연락이 되어 있어야 내부 확인이 가능합니다.</entry>
<entry key="PC.MAL.MI_MT_H_026">연락처</entry>
<entry key="PC.MAL.MI_MT_H_027">증상설명</entry>
<entry key="PC.MAL.MI_MT_H_028">저장</entry>
<entry key="PC.MAL.MI_MT_H_029">취소</entry>
<entry key="PC.MAL.MI_MT_H_030">연락처를 입력해주십시오.</entry>
<entry key="PC.MAL.MI_MT_C_031">확인</entry>
<entry key="PC.MAL.MI_MT_C_032">문의내용을 입력해주십시오.</entry>
<entry key="PC.MAL.MI_MT_C_033">확인</entry>
<entry key="PC.MAL.MI_MT_H_034">메일원문을 고객센터로 접수하시겠습니까?</entry>
<entry key="PC.MAL.MI_MT_H_035">확인</entry>
<entry key="PC.MAL.MI_MT_H_036">취소</entry>
<entry key="PC.MAL.MI_MT_T_037">고객센터로 메일발송이 성공하였습니다.</entry>
<entry key="PC.MAL.MI_MT_H_038">주소록 추가</entry>
<entry key="PC.MAL.MI_MT_T_039">주소록에 등록되었습니다.</entry>
<entry key="PC.MAL.MI_MT_H_040">스팸차단</entry>
<entry key="PC.MAL.MI_MT_H_041">일반 첨부파일 X개</entry>
<entry key="PC.MAL.MI_MT_H_041">대용량 첨부파일 X개</entry>
<entry key="PC.MAL.MI_MT_H_042">모두저장</entry>
<entry key="PC.MAL.MI_MT_H_043">파일명</entry>
<entry key="PC.MAL.MI_MT_H_044">용량</entry>
<entry key="PC.MAL.MI_MT_H_045">다운로드</entry>
<entry key="PC.MAL.MI_MT_C_046">메일을 작성 중입니다. 작성을 중지하고 답장 메일을 쓰시겠습니까?</entry>
<entry key="PC.MAL.MI_MT_C_047">확인</entry>
<entry key="PC.MAL.MI_MT_C_048">취소</entry>
<entry key="PC.MAL.MI_MT_C_049">메일을 작성 중입니다. 작성을 중지하고 전체답장 메일을 쓰시겠습니까?</entry>
<entry key="PC.MAL.MI_MT_C_050">확인</entry>
<entry key="PC.MAL.MI_MT_C_051">취소</entry>
<entry key="PC.MAL.MI_MT_C_052">메일을 작성 중입니다. 작성을 중지하고 전달 메일을 쓰시겠습니까?</entry>
<entry key="PC.MAL.MI_MT_C_053">확인</entry>
<entry key="PC.MAL.MI_MT_C_054">취소</entry>
<entry key="PC.MAL.MI_MT_C_055">메일을 삭제하시겠습니까?</entry>
<entry key="PC.MAL.MI_MT_C_056">확인</entry>
<entry key="PC.MAL.MI_MT_C_057">취소</entry>
<entry key="PC.MAL.MI_MT_T_058">메일이 삭제되었습니다.</entry>
<entry key="PC.MAL.MI_MT_C_059">보낸사람의 이메일주소가 수신거부에 등록 됩니다. 보낸사람을 스팸차단 하시겠습니까?</entry>
<entry key="PC.MAL.MI_MT_C_060">확인</entry>
<entry key="PC.MAL.MI_MT_C_061">취소</entry>
<entry key="PC.MAL.MI_MT_T_062">수신거부 목록에 등록되었습니다.</entry>
<entry key="PC.MAL.MI_MT_T_063">메일이 이동되었습니다.</entry>
<entry key="PC.MAL.MI_SM_H_064">보안메일</entry>
<entry key="PC.MAL.MI_SM_H_065">발신자</entry>
<entry key="PC.MAL.MI_SM_H_066">U+Works(그룹웨어)에서 발송된 보안메일입니다.</entry>
<entry key="PC.MAL.MI_SM_H_067">첨부파일을 열면, 메일 확인 페이지로 이동하게 됩니다.</entry>
<entry key="PC.MAL.MI_SM_H_068">이동된 페이지에서 개인적으로 받으신 인증번호 또는 아래 힌트 기반의 인증번호를 입력하시면 메일 조회가 가능합니다.</entry>
<entry key="PC.MAL.MI_SM_H_069">이 메일은 2주간만 조회 가능합니다. (YYYY-MM-DD까지 유효)</entry>
<entry key="PC.MAL.MI_SM_H_070">Hint</entry>
<entry key="PC.MAL.MI_SM_H_071">비밀 번호가 일치 하지 않습니다. 비밀번호를 확인해 주세요.</entry>
<entry key="PC.MAL.MT_H_001">별표편지함</entry>
<entry key="PC.MAL.MT_H_002">제목</entry>
<entry key="PC.MAL.MT_H_003">보낸사람</entry>
<entry key="PC.MAL.MT_H_004">크기</entry>
<entry key="PC.MAL.MT_H_005">받은날짜</entry>
<entry key="PC.MAL.MT_H_006">총 X건 중 X-X번째</entry>
<entry key="PC.MAL.MT_H_007">전체메일</entry>
<entry key="PC.MAL.MT_H_008">읽지않은메일</entry>
<entry key="PC.MAL.MT_H_009">읽은메일</entry>
<entry key="PC.MAL.MT_H_010">알림 메일제외</entry>
<entry key="PC.MAL.MT_H_011">삭제</entry>
<entry key="PC.MAL.MT_H_012">스팸차단</entry>
<entry key="PC.MAL.MT_H_013">이동</entry>
<entry key="PC.MAL.MT_H_014">상태변경</entry>
<entry key="PC.MAL.MT_H_015">읽음</entry>
<entry key="PC.MAL.MT_H_016">읽지않음</entry>
<entry key="PC.MAL.MT_H_017">추가기능</entry>
<entry key="PC.MAL.MT_H_018">일정 등록</entry>
<entry key="PC.MAL.MT_H_019">할일 요청</entry>
<entry key="PC.MAL.MT_H_020">PC로 저장</entry>
<entry key="PC.MAL.MT_H_021">답장</entry>
<entry key="PC.MAL.MT_H_022">전체답장</entry>
<entry key="PC.MAL.MT_H_023">전달</entry>
<entry key="PC.MAL.MT_C_024">다중전달</entry>
<entry key="PC.MAL.MT_C_024">메일을 삭제하시겠습니까?</entry>
<entry key="PC.MAL.MT_C_025">확인</entry>
<entry key="PC.MAL.MT_C_026">취소</entry>
<entry key="PC.MAL.MT_T_027">메일이 삭제되었습니다.</entry>
<entry key="PC.MAL.MT_C_028">보낸사람의 이메일주소가 수신거부에 등록 됩니다. 보낸사람을 스팸차단 하시겠습니까?</entry>
<entry key="PC.MAL.MT_C_029">확인</entry>
<entry key="PC.MAL.MT_C_030">취소</entry>
<entry key="PC.MAL.MT_T_031">수신거부 목록에 등록되었습니다.</entry>
<entry key="PC.MAL.MT_T_032">메일이 이동되었습니다.</entry>
<entry key="PC.MAL.MT_C_033">메일을 작성 중입니다. 작성을 중지하고 답장 메일을 쓰시겠습니까?</entry>
<entry key="PC.MAL.MT_C_034">확인</entry>
<entry key="PC.MAL.MT_C_035">취소</entry>
<entry key="PC.MAL.MT_C_036">메일을 작성 중입니다. 작성을 중지하고 전체답장 메일을 쓰시겠습니까?</entry>
<entry key="PC.MAL.MT_C_037">확인</entry>
<entry key="PC.MAL.MT_C_038">취소</entry>
<entry key="PC.MAL.MT_C_039">메일을 작성 중입니다. 작성을 중지하고 전달 메일을 쓰시겠습니까?</entry>
<entry key="PC.MAL.MT_C_040">확인</entry>
<entry key="PC.MAL.MT_C_041">취소</entry>
<entry key="PC.MAL.MT_C_042">메일을 작성 중입니다. 작성을 중지하고 다중전달 메일을 쓰시겠습니까?</entry>
<entry key="PC.MAL.MT_C_043">(메일 크기와 개수에 따라 다소 시간이 소요됩니다.)</entry>
<entry key="PC.MAL.MT_C_044">확인</entry>
<entry key="PC.MAL.MT_C_045">취소</entry>
<entry key="PC.MAL.MT_C_046">다중전달 메일을 쓰시겠습니까? (메일 크기와 개수에 따라 다소 시간이 소요됩니다.</entry>
<entry key="PC.MAL.MT_C_047">확인</entry>
<entry key="PC.MAL.MT_C_048">취소</entry>
<entry key="PC.MAL.MT_A_049">다중전달 메일은 10개까지 선택 가능합니다.</entry>
<entry key="PC.MAL.MT_A_050">확인</entry>
<entry key="PC.MAL.MT_MT_H_001">답장</entry>
<entry key="PC.MAL.MT_MT_H_002">전체답장</entry>
<entry key="PC.MAL.MT_MT_H_003">전달</entry>
<entry key="PC.MAL.MT_MT_H_004">삭제</entry>
<entry key="PC.MAL.MT_MT_H_005">스팸차단</entry>
<entry key="PC.MAL.MT_MT_H_006">읽지않음</entry>
<entry key="PC.MAL.MT_MT_H_007">추가기능</entry>
<entry key="PC.MAL.MT_MT_H_008">일정 등록</entry>
<entry key="PC.MAL.MT_MT_H_009">할일 요청</entry>
<entry key="PC.MAL.MT_MT_H_010">PC로 저장</entry>
<entry key="PC.MAL.MT_MT_H_011">인쇄</entry>
<entry key="PC.MAL.MT_MT_H_012">원문보기</entry>
<entry key="PC.MAL.MT_MT_H_013">제목</entry>
<entry key="PC.MAL.MT_MT_H_014">보낸사람</entry>
<entry key="PC.MAL.MT_MT_H_015">받은날짜</entry>
<entry key="PC.MAL.MT_MT_H_016">받는사람</entry>
<entry key="PC.MAL.MT_MT_H_017">첨부파일</entry>
<entry key="PC.MAL.MT_MT_H_018">본문 크기 조절</entry>
<entry key="PC.MAL.MT_MT_H_019">전체</entry>
<entry key="PC.MAL.MT_MT_H_020">A4 세로</entry>
<entry key="PC.MAL.MT_MT_H_021">본문 팝업</entry>
<entry key="PC.MAL.MT_MT_H_022">원문접수</entry>
<entry key="PC.MAL.MT_MT_H_023">원문접수</entry>
<entry key="PC.MAL.MT_MT_H_024">메일 원문을 고객센터로 접수 하기위해서는 아래 정보를 반드시 입력하셔야 하며, 발송 전 고객센터와 연락이 되어 있어야 내부 확인이 가능합니다.</entry>
<entry key="PC.MAL.MT_MT_H_025">연락처</entry>
<entry key="PC.MAL.MT_MT_H_026">증상설명</entry>
<entry key="PC.MAL.MT_MT_H_027">저장</entry>
<entry key="PC.MAL.MT_MT_H_028">취소</entry>
<entry key="PC.MAL.MT_MT_H_029">연락처를 입력해주십시오.</entry>
<entry key="PC.MAL.MT_MT_C_030">확인</entry>
<entry key="PC.MAL.MT_MT_C_031">문의내용을 입력해주십시오.</entry>
<entry key="PC.MAL.MT_MT_C_032">확인</entry>
<entry key="PC.MAL.MT_MT_H_033">메일원문을 고객센터로 접수하시겠습니까?</entry>
<entry key="PC.MAL.MT_MT_H_034">확인</entry>
<entry key="PC.MAL.MT_MT_H_035">취소</entry>
<entry key="PC.MAL.MT_MT_T_036">고객센터로 메일발송이 성공하였습니다.</entry>
<entry key="PC.MAL.MT_MT_H_037">주소록 추가</entry>
<entry key="PC.MAL.MT_MT_T_038">주소록에 등록되었습니다.</entry>
<entry key="PC.MAL.MT_MT_H_039">스팸차단</entry>
<entry key="PC.MAL.MT_MT_H_040">일반 첨부파일 X개</entry>
<entry key="PC.MAL.MT_MT_H_041">대용량 첨부파일 X개</entry>
<entry key="PC.MAL.MT_MT_H_042">모두저장</entry>
<entry key="PC.MAL.MT_MT_H_043">파일명</entry>
<entry key="PC.MAL.MT_MT_H_044">용량</entry>
<entry key="PC.MAL.MT_MT_H_045">다운로드</entry>
<entry key="PC.MAL.MT_MT_C_046">메일을 작성 중입니다. 작성을 중지하고 답장 메일을 쓰시겠습니까?</entry>
<entry key="PC.MAL.MT_MT_C_047">확인</entry>
<entry key="PC.MAL.MT_MT_C_048">취소</entry>
<entry key="PC.MAL.MT_MT_C_049">메일을 작성 중입니다. 작성을 중지하고 전체답장 메일을 쓰시겠습니까?</entry>
<entry key="PC.MAL.MT_MT_C_050">확인</entry>
<entry key="PC.MAL.MT_MT_C_051">취소</entry>
<entry key="PC.MAL.MT_MT_C_052">메일을 작성 중입니다. 작성을 중지하고 전달 메일을 쓰시겠습니까?</entry>
<entry key="PC.MAL.MT_MT_C_053">확인</entry>
<entry key="PC.MAL.MT_MT_C_054">취소</entry>
<entry key="PC.MAL.MT_MT_C_055">메일을 삭제하시겠습니까?</entry>
<entry key="PC.MAL.MT_MT_C_056">확인</entry>
<entry key="PC.MAL.MT_MT_C_057">취소</entry>
<entry key="PC.MAL.MT_MT_T_058">메일이 삭제되었습니다.</entry>
<entry key="PC.MAL.MT_MT_C_059">보낸사람의 이메일주소가 수신거부에 등록 됩니다. 보낸사람을 스팸차단 하시겠습니까?</entry>
<entry key="PC.MAL.MT_MT_C_060">확인</entry>
<entry key="PC.MAL.MT_MT_C_061">취소</entry>
<entry key="PC.MAL.MT_MT_T_062">수신거부 목록에 등록되었습니다.</entry>
<entry key="PC.MAL.MS_H_001">보낸편지함</entry>
<entry key="PC.MAL.MS_H_002">제목</entry>
<entry key="PC.MAL.MS_H_003">받는사람</entry>
<entry key="PC.MAL.MS_H_004">크기</entry>
<entry key="PC.MAL.MS_H_005">보낸날짜</entry>
<entry key="PC.MAL.MS_H_006">총 X건 중 X-X번째</entry>
<entry key="PC.MAL.MS_H_007">삭제</entry>
<entry key="PC.MAL.MS_H_008">이동</entry>
<entry key="PC.MAL.MS_H_009">추가기능</entry>
<entry key="PC.MAL.MS_H_010">일정 등록</entry>
<entry key="PC.MAL.MS_H_011">할일 요청</entry>
<entry key="PC.MAL.MS_H_012">PC로 저장</entry>
<entry key="PC.MAL.MS_H_013">다중전달</entry>
<entry key="PC.MAL.MS_H_014">답장</entry>
<entry key="PC.MAL.MS_H_015">전체답장</entry>
<entry key="PC.MAL.MS_H_016">전달</entry>
<entry key="PC.MAL.MS_H_017">다중전달</entry>
<entry key="PC.MAL.MS_C_018">메일을 삭제하시겠습니까?</entry>
<entry key="PC.MAL.MS_C_019">확인</entry>
<entry key="PC.MAL.MS_C_020">취소</entry>
<entry key="PC.MAL.MS_T_021">메일이 삭제되었습니다.</entry>
<entry key="PC.MAL.MS_C_022">보낸사람의 이메일주소가 수신거부에 등록 됩니다. 보낸사람을 스팸차단 하시겠습니까?</entry>
<entry key="PC.MAL.MS_C_023">확인</entry>
<entry key="PC.MAL.MS_C_024">취소</entry>
<entry key="PC.MAL.MS_T_025">수신거부 목록에 등록되었습니다.</entry>
<entry key="PC.MAL.MS_T_026">메일이 이동되었습니다.</entry>
<entry key="PC.MAL.MS_C_027">메일을 작성 중입니다. 작성을 중지하고 답장 메일을 쓰시겠습니까?</entry>
<entry key="PC.MAL.MS_C_028">확인</entry>
<entry key="PC.MAL.MS_C_029">취소</entry>
<entry key="PC.MAL.MS_C_030">메일을 작성 중입니다. 작성을 중지하고 전체답장 메일을 쓰시겠습니까?</entry>
<entry key="PC.MAL.MS_C_031">확인</entry>
<entry key="PC.MAL.MS_C_032">취소</entry>
<entry key="PC.MAL.MS_C_033">메일을 작성 중입니다. 작성을 중지하고 전달 메일을 쓰시겠습니까?</entry>
<entry key="PC.MAL.MS_C_034">확인</entry>
<entry key="PC.MAL.MS_C_035">취소</entry>
<entry key="PC.MAL.MS_C_036">메일을 작성 중입니다. 작성을 중지하고 다중전달 메일을 쓰시겠습니까?</entry>
<entry key="PC.MAL.MS_C_037">(메일 크기와 개수에 따라 다소 시간이 소요됩니다.)</entry>
<entry key="PC.MAL.MS_C_038">확인</entry>
<entry key="PC.MAL.MS_C_039">취소</entry>
<entry key="PC.MAL.MS_C_040">다중전달 메일을 쓰시겠습니까? (메일 크기와 개수에 따라 다소 시간이 소요됩니다.</entry>
<entry key="PC.MAL.MS_C_041">확인</entry>
<entry key="PC.MAL.MS_C_042">취소</entry>
<entry key="PC.MAL.MS_A_043">다중전달 메일은 10개까지 선택 가능합니다.</entry>
<entry key="PC.MAL.MS_A_044">확인</entry>
<entry key="PC.MAL.MS_MT_H_001">답장</entry>
<entry key="PC.MAL.MS_MT_H_002">전체답장</entry>
<entry key="PC.MAL.MS_MT_H_003">전달</entry>
<entry key="PC.MAL.MS_MT_H_004">재전송</entry>
<entry key="PC.MAL.MS_MT_H_005">삭제</entry>
<entry key="PC.MAL.MS_MT_H_006">이동</entry>
<entry key="PC.MAL.MS_MT_H_007">추가기능</entry>
<entry key="PC.MAL.MS_MT_H_008">일정 등록</entry>
<entry key="PC.MAL.MS_MT_H_009">할일 요청</entry>
<entry key="PC.MAL.MS_MT_H_010">PC로 저장</entry>
<entry key="PC.MAL.MS_MT_H_011">인쇄</entry>
<entry key="PC.MAL.MS_MT_H_012">원문보기</entry>
<entry key="PC.MAL.MS_MT_H_013">보낸사람</entry>
<entry key="PC.MAL.MS_MT_H_014">보낸날짜</entry>
<entry key="PC.MAL.MS_MT_H_015">받는사람</entry>
<entry key="PC.MAL.MS_MT_H_016">숨은참조</entry>
<entry key="PC.MAL.MS_MT_H_017">첨부파일</entry>
<entry key="PC.MAL.MS_MT_H_018">본문 크기 조절</entry>
<entry key="PC.MAL.MS_MT_H_019">전체</entry>
<entry key="PC.MAL.MS_MT_H_020">A4 세로</entry>
<entry key="PC.MAL.MS_MT_H_021">본문 팝업</entry>
<entry key="PC.MAL.MS_MT_H_022">일반 첨부파일 X개</entry>
<entry key="PC.MAL.MS_MT_H_023">모두저장</entry>
<entry key="PC.MAL.MS_MT_H_024">파일명</entry>
<entry key="PC.MAL.MS_MT_H_025">용량</entry>
<entry key="PC.MAL.MS_MT_H_026">다운로드</entry>
<entry key="PC.MAL.MS_MT_C_027">메일을 작성 중입니다. 작성을 중지하고 답장 메일을 쓰시겠습니까?</entry>
<entry key="PC.MAL.MS_MT_C_028">확인</entry>
<entry key="PC.MAL.MS_MT_C_029">취소</entry>
<entry key="PC.MAL.MS_MT_C_030">메일을 작성 중입니다. 작성을 중지하고 전체답장 메일을 쓰시겠습니까?</entry>
<entry key="PC.MAL.MS_MT_C_031">확인</entry>
<entry key="PC.MAL.MS_MT_C_032">취소</entry>
<entry key="PC.MAL.MS_MT_C_033">메일을 작성 중입니다. 작성을 중지하고 전달 메일을 쓰시겠습니까?</entry>
<entry key="PC.MAL.MS_MT_C_034">확인</entry>
<entry key="PC.MAL.MS_MT_C_035">취소</entry>
<entry key="PC.MAL.MS_MT_C_036">메일을 작성 중입니다. 작성을 중지하고 재전송 메일을 쓰시겠습니까?</entry>
<entry key="PC.MAL.MS_MT_C_037">확인</entry>
<entry key="PC.MAL.MS_MT_C_038">취소</entry>
<entry key="PC.MAL.MS_MT_C_039">메일을 삭제하시겠습니까?</entry>
<entry key="PC.MAL.MS_MT_C_040">확인</entry>
<entry key="PC.MAL.MS_MT_C_041">취소</entry>
<entry key="PC.MAL.MS_MT_T_042">메일이 삭제되었습니다.</entry>
<entry key="PC.MAL.MS_MT_T_043">메일이 이동되었습니다.</entry>
<entry key="PC.MAL.MS_RC_H_001">수신확인</entry>
<entry key="PC.MAL.MS_RC_H_002">수신확인의 보관기간은 3개월 보관합니다.</entry>
<entry key="PC.MAL.MS_RC_H_003">수신자의 클라이언트(웹, 아웃룩 등등) 환경에 따라 정상적으로 확인이 안될 수 있습니다.</entry>
<entry key="PC.MAL.MS_RC_H_004">제목</entry>
<entry key="PC.MAL.MS_RC_H_005">받는사람</entry>
<entry key="PC.MAL.MS_RC_H_006">확인날짜</entry>
<entry key="PC.MAL.MS_RC_H_007">보낸날짜</entry>
<entry key="PC.MAL.MS_RC_H_008">총 X건 중 X-X번째</entry>
<entry key="PC.MAL.MS_RC_H_009">읽지않음</entry>
<entry key="PC.MAL.MS_RC_H_010">일부읽음</entry>
<entry key="PC.MAL.MS_RC_H_011">모두취소</entry>
<entry key="PC.MAL.MS_RC_H_012">삭제</entry>
<entry key="PC.MAL.MS_RC_C_013">수신확인을 삭제하시겠습니까?</entry>
<entry key="PC.MAL.MS_RC_C_014">확인</entry>
<entry key="PC.MAL.MS_RC_C_015">취소</entry>
<entry key="PC.MAL.MS_RC_T_016">수신확인이 삭제되었습니다.</entry>
<entry key="PC.MAL.MS_RC_H_017">수신자 목록</entry>
<entry key="PC.MAL.MS_RC_H_018">내부로 보낸 메일의 경우 도착 시간 기준으로 24시간 이내의 메일만 회수 가능합니다.</entry>
<entry key="PC.MAL.MS_RC_H_019">외부로 발송한 메일은 회수가 불가능합니다.</entry>
<entry key="PC.MAL.MS_RC_H_020">메일회수</entry>
<entry key="PC.MAL.MS_RC_C_021">수신자의 수에 따라 회수 시간이 소요됩니다. 메일을 회수하시겠습니까?</entry>
<entry key="PC.MAL.MS_RC_C_022">확인</entry>
<entry key="PC.MAL.MS_RC_C_023">취소</entry>
<entry key="PC.MAL.MS_RC_H_024">받는사람</entry>
<entry key="PC.MAL.MS_RC_H_025">확인날짜</entry>
<entry key="PC.MAL.MS_RC_H_026">발송취소</entry>
<entry key="PC.MAL.MS_RC_H_027">읽지않음</entry>
<entry key="PC.MAL.MD_H_001">임시보관함</entry>
<entry key="PC.MAL.MD_H_002">제목</entry>
<entry key="PC.MAL.MD_H_003">받는사람</entry>
<entry key="PC.MAL.MD_H_004">크기</entry>
<entry key="PC.MAL.MD_H_005">보관날짜</entry>
<entry key="PC.MAL.MD_H_006">총 x건 중 X-X번째</entry>
<entry key="PC.MAL.MD_H_007">완전삭제</entry>
<entry key="PC.MAL.MD_C_008">메일을 삭제하시겠습니까?</entry>
<entry key="PC.MAL.MD_C_009">확인</entry>
<entry key="PC.MAL.MD_C_010">취소</entry>
<entry key="PC.MAL.MD_T_011">메일이 삭제되었습니다.</entry>
<entry key="PC.MAL.MD_C_012">메일을 작성 중입니다. 작성을 중지하고 임시메일을 쓰시겠습니까?</entry>
<entry key="PC.MAL.MD_C_013">확인</entry>
<entry key="PC.MAL.MD_C_014">취소</entry>
<entry key="PC.MAL.MH_H_001">예약발송함</entry>
<entry key="PC.MAL.MH_H_002">제목</entry>
<entry key="PC.MAL.MH_H_003">받는사람</entry>
<entry key="PC.MAL.MH_H_004">크기</entry>
<entry key="PC.MAL.MH_H_005">예약날짜</entry>
<entry key="PC.MAL.MH_H_006">총 x건 중 X-X번째</entry>
<entry key="PC.MAL.MH_H_007">발송 취소</entry>
<entry key="PC.MAL.MH_C_008">메일발송을 취소하시겠습니까?</entry>
<entry key="PC.MAL.MH_C_009">확인</entry>
<entry key="PC.MAL.MH_C_010">취소</entry>
<entry key="PC.MAL.MH_T_011">메일이 삭제되었습니다.</entry>
<entry key="PC.MAL.MH_C_012">메일을 작성 중입니다. 작성을 중지하고 예약메일을 쓰시겠습니까?</entry>
<entry key="PC.MAL.MH_C_013">확인</entry>
<entry key="PC.MAL.MH_C_014">취소</entry>
<entry key="PC.MAL.TR_H_001">휴지통</entry>
<entry key="PC.MAL.TR_H_002">제목</entry>
<entry key="PC.MAL.TR_H_003">보낸사람</entry>
<entry key="PC.MAL.TR_H_004">크기</entry>
<entry key="PC.MAL.TR_H_005">받은날짜</entry>
<entry key="PC.MAL.TR_H_006">총 x건 중 X-X번째</entry>
<entry key="PC.MAL.TR_H_007">비우기</entry>
<entry key="PC.MAL.TR_H_008">완전삭제</entry>
<entry key="PC.MAL.TR_H_009">스팸차단</entry>
<entry key="PC.MAL.TR_H_010">이동</entry>
<entry key="PC.MAL.TR_H_011">추가기능</entry>
<entry key="PC.MAL.TR_H_012">PC로 저장</entry>
<entry key="PC.MAL.TR_C_013">메일함의 모든 내용이 삭제됩니다. 삭제하시겠습니까?</entry>
<entry key="PC.MAL.TR_C_014">확인</entry>
<entry key="PC.MAL.TR_C_015">취소</entry>
<entry key="PC.MAL.TR_T_016">선택한 메일함의 모든 메일이 삭제되었습니다.</entry>
<entry key="PC.MAL.TR_C_017">메일을 삭제하시겠습니까?</entry>
<entry key="PC.MAL.TR_C_018">확인</entry>
<entry key="PC.MAL.TR_C_019">취소</entry>
<entry key="PC.MAL.TR_T_020">메일이 삭제되었습니다.</entry>
<entry key="PC.MAL.TR_C_021">보낸사람의 이메일주소가 수신거부에 등록 됩니다. 보낸사람을 스팸차단 하시겠습니까?</entry>
<entry key="PC.MAL.TR_C_022">확인</entry>
<entry key="PC.MAL.TR_C_023">취소</entry>
<entry key="PC.MAL.TR_T_024">수신거부 목록에 등록되었습니다.</entry>
<entry key="PC.MAL.TR_T_025">메일이 이동되었습니다.</entry>
<entry key="PC.MAL.TR_TT_H_001">완전삭제</entry>
<entry key="PC.MAL.TR_TT_H_002">스팸차단</entry>
<entry key="PC.MAL.TR_TT_H_003">이동</entry>
<entry key="PC.MAL.TR_TT_H_004">추가기능</entry>
<entry key="PC.MAL.TR_TT_H_005">PC로 저장</entry>
<entry key="PC.MAL.TR_TT_H_006">제목</entry>
<entry key="PC.MAL.TR_TT_H_007">보낸사람</entry>
<entry key="PC.MAL.TR_TT_H_008">제목</entry>
<entry key="PC.MAL.TR_TT_H_009">보낸사람</entry>
<entry key="PC.MAL.TR_TT_H_010">받은날짜</entry>
<entry key="PC.MAL.TR_TT_H_011">받는사람</entry>
<entry key="PC.MAL.TR_TT_H_012">첨부파일</entry>
<entry key="PC.MAL.TR_TT_H_013">본문 크기 조절</entry>
<entry key="PC.MAL.TR_TT_H_014">전체</entry>
<entry key="PC.MAL.TR_TT_H_015">A4 세로</entry>
<entry key="PC.MAL.TR_TT_H_016">본문 팝업</entry>
<entry key="PC.MAL.TR_TT_H_017">일반 첨부파일 X개</entry>
<entry key="PC.MAL.TR_TT_H_018">모두저장</entry>
<entry key="PC.MAL.TR_TT_H_019">파일명</entry>
<entry key="PC.MAL.TR_TT_H_020">용량</entry>
<entry key="PC.MAL.TR_TT_H_021">다운로드</entry>
<entry key="PC.MAL.TR_TT_C_022">메일을 삭제하시겠습니까?</entry>
<entry key="PC.MAL.TR_TT_C_023">확인</entry>
<entry key="PC.MAL.TR_TT_C_024">취소</entry>
<entry key="PC.MAL.TR_TT_T_025">메일이 삭제되었습니다.</entry>
<entry key="PC.MAL.TR_TT_C_026">보낸사람의 이메일주소가 수신거부에 등록 됩니다. 보낸사람을 스팸차단 하시겠습니까?</entry>
<entry key="PC.MAL.TR_TT_C_027">확인</entry>
<entry key="PC.MAL.TR_TT_C_028">취소</entry>
<entry key="PC.MAL.TR_TT_T_029">수신거부 목록에 등록되었습니다.</entry>
<entry key="PC.MAL.TR_TT_T_030">메일이 이동되었습니다.</entry>
<entry key="PC.MAL.SP_H_001">스팸편지함</entry>
<entry key="PC.MAL.SP_H_001">제목</entry>
<entry key="PC.MAL.SP_H_002">보낸사람</entry>
<entry key="PC.MAL.SP_H_003">크기</entry>
<entry key="PC.MAL.SP_H_004">받은날짜</entry>
<entry key="PC.MAL.SP_H_005">총 X건 중 X-X번째</entry>
<entry key="PC.MAL.SP_H_006">전체메일</entry>
<entry key="PC.MAL.SP_H_007">읽지않은메일</entry>
<entry key="PC.MAL.SP_H_008">읽은메일</entry>
<entry key="PC.MAL.SP_H_009">알림 메일제외</entry>
<entry key="PC.MAL.SP_H_010">완전삭제</entry>
<entry key="PC.MAL.SP_H_011">스팸해제</entry>
<entry key="PC.MAL.SP_H_012">이동</entry>
<entry key="PC.MAL.SP_H_013">추가기능</entry>
<entry key="PC.MAL.SP_H_014">PC로 저장</entry>
<entry key="PC.MAL.SP_C_015">메일을 삭제하시겠습니까?</entry>
<entry key="PC.MAL.SP_C_016">확인</entry>
<entry key="PC.MAL.SP_C_017">취소</entry>
<entry key="PC.MAL.SP_T_018">메일이 삭제되었습니다.</entry>
<entry key="PC.MAL.SP_C_019">보낸사람의 이메일주소가 수신허용에 등록 됩니다. 보낸사람을 스팸해제 하시겠습니까?</entry>
<entry key="PC.MAL.SP_C_020">확인</entry>
<entry key="PC.MAL.SP_C_021">취소</entry>
<entry key="PC.MAL.SP_T_022">스팸해제 되었습니다.</entry>
<entry key="PC.MAL.SP_T_023">메일이 이동되었습니다.</entry>
<entry key="PC.MAL.SP_ST_H_001">완전삭제</entry>
<entry key="PC.MAL.SP_ST_H_002">스팸해제</entry>
<entry key="PC.MAL.SP_ST_H_003">이동</entry>
<entry key="PC.MAL.SP_ST_H_004">추가기능</entry>
<entry key="PC.MAL.SP_ST_H_005">PC로 저장</entry>
<entry key="PC.MAL.SP_ST_H_006">원문보기</entry>
<entry key="PC.MAL.SP_ST_H_007">보낸사람</entry>
<entry key="PC.MAL.SP_ST_H_008">받은날짜</entry>
<entry key="PC.MAL.SP_ST_H_009">받는사람</entry>
<entry key="PC.MAL.SP_ST_H_010">첨부파일</entry>
<entry key="PC.MAL.SP_ST_H_011">본문 크기 조절</entry>
<entry key="PC.MAL.SP_ST_H_012">전체</entry>
<entry key="PC.MAL.SP_ST_H_013">A4 세로</entry>
<entry key="PC.MAL.SP_ST_H_014">본문 팝업</entry>
<entry key="PC.MAL.SP_ST_H_015">원문접수</entry>
<entry key="PC.MAL.SP_ST_H_016">주소록 추가</entry>
<entry key="PC.MAL.SP_ST_H_017">스팸해제</entry>
<entry key="PC.MAL.SP_ST_H_018">일반 첨부파일 X개</entry>
<entry key="PC.MAL.SP_ST_H_019">모두저장</entry>
<entry key="PC.MAL.SP_ST_H_020">파일명</entry>
<entry key="PC.MAL.SP_ST_H_021">용량</entry>
<entry key="PC.MAL.SP_ST_H_022">다운로드</entry>
<entry key="PC.MAL.SP_ST_C_023">메일을 삭제하시겠습니까?</entry>
<entry key="PC.MAL.SP_ST_C_024">확인</entry>
<entry key="PC.MAL.SP_ST_C_025">취소</entry>
<entry key="PC.MAL.SP_ST_T_026">메일이 삭제되었습니다.</entry>
<entry key="PC.MAL.SP_ST_C_027">보낸사람의 이메일주소가 수신허용에 등록 됩니다. 보낸사람을 스팸해제 하시겠습니까?</entry>
<entry key="PC.MAL.SP_ST_C_028">확인</entry>
<entry key="PC.MAL.SP_ST_C_029">취소</entry>
<entry key="PC.MAL.SP_ST_T_030">스팸해제 되었습니다.</entry>
<entry key="PC.MAL.SP_ST_T_031">메일이 이동되었습니다.</entry>
<entry key="PC.MAL.UM_ST_H_001">사용자 편지함</entry>
<entry key="PC.MAL.UM_ST_T_002">사용자 편지함이 추가되었습니다.</entry>
<entry key="PC.MAL.UM_ST_H_003">수정</entry>
<entry key="PC.MAL.UM_ST_T_004">사용자 편지함 이름이 변경되었습니다.</entry>
<entry key="PC.MAL.UM_ST_H_005">삭제</entry>
<entry key="PC.MAL.UM_ST_C_006">메일함의 모든 메일도 함께 삭제됩니다. 삭제하시겠습니까?</entry>
<entry key="PC.MAL.UM_ST_C_007">확인</entry>
<entry key="PC.MAL.UM_ST_C_008">취소</entry>
<entry key="PC.MAL.UM_ST_T_009">사용자 편지함이 삭제되었습니다.</entry>
<entry key="PC.MAL.UM_ST_H_010">공유</entry>
<entry key="PC.MAL.UM_ST_H_011">편지함 공유</entry>
<entry key="PC.MAL.UM_ST_H_012">편지함</entry>
<entry key="PC.MAL.UM_ST_H_013">공유대상</entry>
<entry key="PC.MAL.UM_ST_H_014">조직도</entry>
<entry key="PC.MAL.UM_ST_H_015">공유대상 선택</entry>
<entry key="PC.MAL.UM_ST_H_016">조직도</entry>
<entry key="PC.MAL.UM_ST_H_017">검색</entry>
<entry key="PC.MAL.UM_ST_H_018">전사관리자</entry>
<entry key="PC.MAL.UM_ST_H_019">부서장</entry>
<entry key="PC.MAL.UM_ST_H_020">총 X명 선택</entry>
<entry key="PC.MAL.UM_ST_H_021">삭제</entry>
<entry key="PC.MAL.UM_ST_H_022">적용</entry>
<entry key="PC.MAL.UM_ST_H_023">취소</entry>
<entry key="PC.MAL.UM_ST_T_024">선택한 공유자를 저장하였습니다.</entry>
<entry key="PC.MAL.SH_ST_H_001">공유받은 편지함</entry>
<entry key="PC.MAL.SH_ST_H_002">복사</entry>
<entry key="PC.MAL.SH_ST_T_003">메일이 복사되었습니다.</entry>
<entry key="PC.MAL.MO_H_001">외부 메일 가져오기</entry>
<entry key="PC.MAL.MO_H_002">외부 메일 가져오기를 신청하거나 취소할 수 있습니다.(진행 중에는 취소 불가)</entry>
<entry key="PC.MAL.MO_H_003">외부 메일 건 수가 많거나 용량이 큰 경우 가져오기 시간이 오래걸릴 수 있으며, 가져오기 완료 후 완료 안내 메일이 발송됩니다.</entry>
<entry key="PC.MAL.MO_H_004">외부 메일 설정은 "사용자 환경설정 > 서비스 설정 > 메일 > 외부 메일 가져오기 탭"에서 할 수 있습니다.</entry>
<entry key="PC.MAL.MO_H_005">이름</entry>
<entry key="PC.MAL.MO_H_006">아이디</entry>
<entry key="PC.MAL.MO_H_007">진행 상태</entry>
<entry key="PC.MAL.MO_H_008">신청 / 취소</entry>
<entry key="PC.MAL.MO_H_009">저장 편지함</entry>
<entry key="PC.MAL.MO_H_010">페이지 당 항목수</entry>
<entry key="PC.MAL.MO_H_011">총 X건 중 X-X번째</entry>
<entry key="PC.MAL.MO_H_012">데이터가 없습니다.</entry>
<entry key="PC.MAL.MO_H_013">외부메일 가져오기는 필요 시, 수동으로 신청하셔야 합니다. 수시로 기능 사용 시, 메일 서비스에 트래픽을 유발시켜 메일 서비스에 부하를 주므로, 자동으로 가져오도록 설정이 불가합니다.</entry>
<entry key="PC.MAL.SM_H_001">제목, 보낸사람, 받는사람, 참조를 입력하세요.</entry>
<entry key="PC.MAL.SM_H_002">상세</entry>
<entry key="PC.MAL.SM_H_003">편지함선택</entry>
<entry key="PC.MAL.SM_H_004">전체편지함</entry>
<entry key="PC.MAL.SM_H_005">받은편지함</entry>
<entry key="PC.MAL.SM_H_006">보낸편지함</entry>
<entry key="PC.MAL.SM_H_007">임시보관함</entry>
<entry key="PC.MAL.SM_H_008">예약발송함</entry>
<entry key="PC.MAL.SM_H_009">휴지통</entry>
<entry key="PC.MAL.SM_H_010">스팸편지함</entry>
<entry key="PC.MAL.SM_H_011">검색어를 입력하세요.</entry>
<entry key="PC.MAL.SM_H_012">검색</entry>
<entry key="PC.MAL.SM_H_013">대상</entry>
<entry key="PC.MAL.SM_H_014">제목</entry>
<entry key="PC.MAL.SM_H_015">내용</entry>
<entry key="PC.MAL.SM_H_016">첨부파일명</entry>
<entry key="PC.MAL.SM_H_017">보낸사람</entry>
<entry key="PC.MAL.SM_H_018">받는사람(참조)</entry>
<entry key="PC.MAL.SM_H_019">기간</entry>
<entry key="PC.MAL.SM_H_020">전체</entry>
<entry key="PC.MAL.SM_H_021">1개월</entry>
<entry key="PC.MAL.SM_H_022">3개월</entry>
<entry key="PC.MAL.SM_H_023">6개월</entry>
<entry key="PC.MAL.SM_H_024">1년</entry>
<entry key="PC.MAL.SM_A_025">검색어를 입력하세요.</entry>
<entry key="PC.MAL.SM_A_026">확인</entry>
<entry key="PC.MAL.SM_RE_H_027">검색결과</entry>
<entry key="PC.MAL.SM_RE_H_028">편지함</entry>
<entry key="PC.MAL.SM_RE_H_029">제목/본문</entry>
<entry key="PC.MAL.SM_RE_H_030">보낸/받는사람</entry>
<entry key="PC.MAL.SM_RE_H_031">받은/보낸날짜</entry>
<entry key="PC.MAL.SM_RE_H_032">검색결과가 없습니다.</entry>

</properties>